COPYING
LICENSE
MANIFEST.in
README
setup.py
src/phishtank/__init__.py
src/phishtank.egg-info/PKG-INFO
src/phishtank.egg-info/SOURCES.txt
src/phishtank.egg-info/dependency_links.txt
src/phishtank.egg-info/top_level.txt