Metadata-Version: 1.0
Name: phishtank
Version: 1.0.0
Summary: Simple python interface for interacting with PhishTank
Home-page: http://bitbucket.org/ashcrow/python-phishtank/
Author: Steve 'Ashcrow' Milner
Author-email: stevem@gnulinux.net
License: New BSD
Download-URL: http://bitbucket.org/ashcrow/python-phishtank/downloads/
Platform: UNKNOWN
Classifier: License :: OSI Approved :: BSD License
Classifier: Development Status :: 5 - Production/Stable
Classifier: Intended Audience :: Developers
Classifier: Intended Audience :: System Administrators
Classifier: Programming Language :: Python
Classifier: Topic :: Security
Classifier: Topic :: Software Development :: Libraries :: Python Modules
